LICENSE.txt
MANIFEST.in
README.md
setup.py
interpretableai/__init__.py
interpretableai/__main__.py
interpretableai/convert.jl
interpretableai/heuristics.py
interpretableai/iai.py
interpretableai/iaibase.py
interpretableai/iaitrees.py
interpretableai/installation.py
interpretableai/mixeddata.py
interpretableai/optimalfeatureselection.py
interpretableai/optimaltrees.py
interpretableai/optimpute.py
interpretableai/predictor.py
interpretableai/rewardestimation.py
interpretableai/setup.jl
interpretableai.egg-info/PKG-INFO
interpretableai.egg-info/SOURCES.txt
interpretableai.egg-info/dependency_links.txt
interpretableai.egg-info/not-zip-safe
interpretableai.egg-info/requires.txt
interpretableai.egg-info/top_level.txt