Metadata-Version: 2.1
Name: interpretableai
Version: 2.8.0
Summary: Interface to Interpretable AI modules in Python
Home-page: https://docs.interpretable.ai/stable/IAI-Python/
Author: Interpretable AI
Author-email: info@interpretable.ai
License: MIT
Platform: UNKNOWN
Classifier: Development Status :: 5 - Production/Stable
Classifier: Intended Audience :: Science/Research
Classifier: Topic :: Scientific/Engineering :: Artificial Intelligence
Classifier: License :: OSI Approved :: MIT License
Classifier: Programming Language :: Python :: 3
Requires-Python: >=3.5
